{
  "reflection": [
    {
      "type": "com.drew.metadata.exif.ExifIFD0Directory",
      "methods": [
        {
          "name": "<init>",
          "parameterTypes": []
        }
      ]
    },
    {
      "type": "com.drew.metadata.exif.ExifInteropDirectory",
      "methods": [
        {
          "name": "<init>",
          "parameterTypes": []
        }
      ]
    },
    {
      "type": "com.drew.metadata.exif.ExifSubIFDDirectory",
      "methods": [
        {
          "name": "<init>",
          "parameterTypes": []
        }
      ]
    },
    {
      "type": "com.github.benmanes.caffeine.cache.BBHeader$ReadAndWriteCounterRef",
      "fields": [
        {
          "name": "writeCounter"
        }
      ]
    },
    {
      "type": "com.github.benmanes.caffeine.cache.BBHeader$ReadCounterRef",
      "fields": [
        {
          "name": "readCounter"
        }
      ]
    },
    {
      "type": "com.github.benmanes.caffeine.cache.BLCHeader$DrainStatusRef",
      "fields": [
        {
          "name": "drainStatus"
        }
      ]
    },
    {
      "type": "com.github.benmanes.caffeine.cache.BaseMpscLinkedArrayQueueColdProducerFields",
      "fields": [
        {
          "name": "producerLimit"
        }
      ]
    },
    {
      "type": "com.github.benmanes.caffeine.cache.BaseMpscLinkedArrayQueueConsumerFields",
      "fields": [
        {
          "name": "consumerIndex"
        }
      ]
    },
    {
      "type": "com.github.benmanes.caffeine.cache.BaseMpscLinkedArrayQueueProducerFields",
      "fields": [
        {
          "name": "producerIndex"
        }
      ]
    },
    {
      "type": "com.github.benmanes.caffeine.cache.BoundedLocalCache",
      "fields": [
        {
          "name": "refreshes"
        }
      ]
    },
    {
      "type": "com.github.benmanes.caffeine.cache.PS",
      "fields": [
        {
          "name": "key"
        },
        {
          "name": "value"
        }
      ]
    },
    {
      "type": "com.github.benmanes.caffeine.cache.PSMS",
      "methods": [
        {
          "name": "<init>",
          "parameterTypes": []
        }
      ]
    },
    {
      "type": "com.github.benmanes.caffeine.cache.SSMS",
      "fields": [
        {
          "name": "FACTORY"
        }
      ]
    },
    {
      "type": "com.github.benmanes.caffeine.cache.StripedBuffer",
      "fields": [
        {
          "name": "tableBusy"
        }
      ]
    },
    {
      "type": "com.sun.glass.ui.Application"
    },
    {
      "type": "com.sun.glass.ui.Menu"
    },
    {
      "type": "com.sun.glass.ui.MenuItem$Callback"
    },
    {
      "type": "com.sun.glass.ui.Size"
    },
    {
      "type": "com.sun.glass.ui.View"
    },
    {
      "type": "com.sun.javafx.font.coretext.CTFactory",
      "methods": [
        {
          "name": "getFactory",
          "parameterTypes": []
        }
      ]
    },
    {
      "type": "com.sun.javafx.logging.PrintLogger",
      "methods": [
        {
          "name": "createInstance",
          "parameterTypes": []
        }
      ]
    },
    {
      "type": "com.sun.javafx.logging.jfr.JFRPulseLogger",
      "methods": [
        {
          "name": "createInstance",
          "parameterTypes": []
        }
      ]
    },
    {
      "type": "com.sun.javafx.scene.control.skin.Utils",
      "methods": [
        {
          "name": "getResource",
          "parameterTypes": [
            "java.lang.String"
          ]
        }
      ]
    },
    {
      "type": "com.sun.javafx.tk.quantum.QuantumToolkit",
      "methods": [
        {
          "name": "<init>",
          "parameterTypes": []
        }
      ]
    },
    {
      "type": "com.sun.org.apache.xerces.internal.jaxp.DocumentBuilderFactoryImpl",
      "methods": [
        {
          "name": "<init>",
          "parameterTypes": []
        }
      ]
    },
    {
      "type": "com.sun.prism.GraphicsPipeline",
      "methods": [
        {
          "name": "getFontFactory",
          "parameterTypes": []
        },
        {
          "name": "getPipeline",
          "parameterTypes": []
        }
      ]
    },
    {
      "type": "com.sun.prism.shader.FillPgram_Color_Loader",
      "methods": [
        {
          "name": "loadShader",
          "parameterTypes": [
            "com.sun.prism.ps.ShaderFactory",
            "java.lang.String",
            "java.io.InputStream"
          ]
        }
      ]
    },
    {
      "type": "com.sun.prism.shader.FillRoundRect_Color_Loader",
      "methods": [
        {
          "name": "loadShader",
          "parameterTypes": [
            "com.sun.prism.ps.ShaderFactory",
            "java.lang.String",
            "java.io.InputStream"
          ]
        }
      ]
    },
    {
      "type": "com.sun.prism.shader.FillRoundRect_LinearGradient_PAD_Loader",
      "methods": [
        {
          "name": "loadShader",
          "parameterTypes": [
            "com.sun.prism.ps.ShaderFactory",
            "java.lang.String",
            "java.io.InputStream"
          ]
        }
      ]
    },
    {
      "type": "com.sun.prism.shader.Solid_TextureRGB_Loader",
      "methods": [
        {
          "name": "loadShader",
          "parameterTypes": [
            "com.sun.prism.ps.ShaderFactory",
            "java.lang.String",
            "java.io.InputStream"
          ]
        }
      ]
    },
    {
      "type": "com.sun.prism.shader.Texture_Color_Loader",
      "methods": [
        {
          "name": "loadShader",
          "parameterTypes": [
            "com.sun.prism.ps.ShaderFactory",
            "java.lang.String",
            "java.io.InputStream"
          ]
        }
      ]
    },
    {
      "type": "com.sun.prism.shader.Texture_LinearGradient_PAD_Loader",
      "methods": [
        {
          "name": "loadShader",
          "parameterTypes": [
            "com.sun.prism.ps.ShaderFactory",
            "java.lang.String",
            "java.io.InputStream"
          ]
        }
      ]
    },
    {
      "type": "com.sun.scenario.effect.impl.prism.PrRenderer",
      "methods": [
        {
          "name": "createRenderer",
          "parameterTypes": [
            "com.sun.scenario.effect.FilterContext"
          ]
        }
      ]
    },
    {
      "type": "com.sun.scenario.effect.impl.prism.ps.PPSLinearConvolveShadowPeer",
      "methods": [
        {
          "name": "<init>",
          "parameterTypes": [
            "com.sun.scenario.effect.FilterContext",
            "com.sun.scenario.effect.impl.Renderer",
            "java.lang.String"
          ]
        }
      ]
    },
    {
      "type": "com.sun.scenario.effect.impl.prism.ps.PPSRenderer",
      "methods": [
        {
          "name": "createRenderer",
          "parameterTypes": [
            "com.sun.scenario.effect.FilterContext"
          ]
        }
      ]
    },
    {
      "type": "java.lang.Character",
      "methods": [
        {
          "name": "isIdeographic",
          "parameterTypes": [
            "int"
          ]
        }
      ]
    },
    {
      "type": "java.lang.Runnable"
    },
    {
      "type": "java.lang.String"
    },
    {
      "type": "java.lang.System",
      "methods": [
        {
          "name": "getSecurityManager",
          "parameterTypes": []
        }
      ]
    },
    {
      "type": "java.nio.ByteBuffer",
      "methods": [
        {
          "name": "order",
          "parameterTypes": [
            "java.nio.ByteOrder"
          ]
        }
      ]
    },
    {
      "type": "java.nio.ByteOrder",
      "methods": [
        {
          "name": "nativeOrder",
          "parameterTypes": []
        }
      ]
    },
    {
      "type": "javafx.animation.Interpolator"
    },
    {
      "type": "javafx.animation.KeyValue"
    },
    {
      "type": "javafx.scene.Camera"
    },
    {
      "type": "javafx.scene.Group"
    },
    {
      "type": "javafx.scene.Node"
    },
    {
      "type": "javafx.scene.ParallelCamera"
    },
    {
      "type": "javafx.scene.Parent"
    },
    {
      "type": "javafx.scene.Scene"
    },
    {
      "type": "javafx.scene.control.Control"
    },
    {
      "type": "javafx.scene.control.Labeled"
    },
    {
      "type": "javafx.scene.effect.Effect"
    },
    {
      "type": "javafx.scene.image.Image"
    },
    {
      "type": "javafx.scene.image.ImageView"
    },
    {
      "type": "javafx.scene.layout.Pane"
    },
    {
      "type": "javafx.scene.layout.Region"
    },
    {
      "type": "javafx.scene.shape.Circle"
    },
    {
      "type": "javafx.scene.shape.LineTo"
    },
    {
      "type": "javafx.scene.shape.MoveTo"
    },
    {
      "type": "javafx.scene.shape.Path"
    },
    {
      "type": "javafx.scene.shape.PathElement"
    },
    {
      "type": "javafx.scene.shape.Rectangle"
    },
    {
      "type": "javafx.scene.shape.SVGPath"
    },
    {
      "type": "javafx.scene.shape.Shape"
    },
    {
      "type": "javafx.scene.text.Font"
    },
    {
      "type": "javafx.scene.text.Text"
    },
    {
      "type": "javafx.scene.transform.Transform"
    },
    {
      "type": "javafx.stage.PopupWindow"
    },
    {
      "type": "javafx.stage.Stage"
    },
    {
      "type": "javafx.stage.Window"
    },
    {
      "type": "javax.imageio.spi.ImageReaderSpi"
    },
    {
      "type": "javax.imageio.spi.ImageWriterSpi"
    },
    {
      "type": "klik.Klik_application",
      "methods": [
        {
          "name": "<init>",
          "parameterTypes": []
        }
      ]
    },
    {
      "type": "sun.java2d.marlin.DMarlinRenderingEngine",
      "methods": [
        {
          "name": "<init>",
          "parameterTypes": []
        }
      ]
    },
    {
      "type": "sun.misc.Unsafe",
      "fields": [
        {
          "name": "theUnsafe"
        }
      ]
    },
    {
      "type": "sun.security.provider.MD5",
      "methods": [
        {
          "name": "<init>",
          "parameterTypes": []
        }
      ]
    },
    {
      "type": "sun.security.provider.NativePRNG",
      "methods": [
        {
          "name": "<init>",
          "parameterTypes": [
            "java.security.SecureRandomParameters"
          ]
        }
      ]
    },
    {
      "type": "sun.security.provider.SHA",
      "methods": [
        {
          "name": "<init>",
          "parameterTypes": []
        }
      ]
    }
  ],
  "resources": [
    {
      "glob": "META-INF/fonts.mf"
    },
    {
      "glob": "META-INF/services/java.lang.System$LoggerFinder"
    },
    {
      "glob": "META-INF/services/java.time.zone.ZoneRulesProvider"
    },
    {
      "glob": "META-INF/services/java.util.spi.ResourceBundleControlProvider"
    },
    {
      "glob": "META-INF/services/javax.imageio.spi.ImageInputStreamSpi"
    },
    {
      "glob": "META-INF/services/javax.imageio.spi.ImageOutputStreamSpi"
    },
    {
      "glob": "META-INF/services/javax.imageio.spi.ImageReaderSpi"
    },
    {
      "glob": "META-INF/services/javax.imageio.spi.ImageTranscoderSpi"
    },
    {
      "glob": "META-INF/services/javax.imageio.spi.ImageWriterSpi"
    },
    {
      "glob": "META-INF/services/javax.xml.parsers.DocumentBuilderFactory"
    },
    {
      "glob": "com/sun/glass/utils/NativeLibLoader.class"
    },
    {
      "glob": "com/sun/javafx/scene/control/skin/modena/modena.bss"
    },
    {
      "glob": "com/sun/javafx/scene/control/skin/resources/controls.properties"
    },
    {
      "glob": "com/sun/javafx/scene/control/skin/resources/controls_en.properties"
    },
    {
      "glob": "com/sun/javafx/scene/control/skin/resources/controls_en_US.properties"
    },
    {
      "glob": "com/sun/javafx/tk/quantum/QuantumMessagesBundle.properties"
    },
    {
      "glob": "com/sun/javafx/tk/quantum/QuantumMessagesBundle_en.properties"
    },
    {
      "glob": "com/sun/javafx/tk/quantum/QuantumMessagesBundle_en_US.properties"
    },
    {
      "glob": "com/sun/prism/es2/glsl/FillPgram_Color.frag"
    },
    {
      "glob": "com/sun/prism/es2/glsl/FillRoundRect_Color.frag"
    },
    {
      "glob": "com/sun/prism/es2/glsl/FillRoundRect_LinearGradient_PAD.frag"
    },
    {
      "glob": "com/sun/prism/es2/glsl/Solid_TextureRGB.frag"
    },
    {
      "glob": "com/sun/prism/es2/glsl/Texture_Color.frag"
    },
    {
      "glob": "com/sun/prism/es2/glsl/Texture_LinearGradient_PAD.frag"
    },
    {
      "glob": "com/sun/scenario/effect/impl/es2/glsl/LinearConvolveShadow_20.frag"
    },
    {
      "glob": "com/sun/scenario/effect/impl/es2/glsl/LinearConvolveShadow_64.frag"
    },
    {
      "glob": "klik.png"
    },
    {
      "glob": "klik/MessagesBundle.properties"
    },
    {
      "glob": "klik/MessagesBundle_en.properties"
    },
    {
      "glob": "klik/MessagesBundle_en_US.properties"
    },
    {
      "glob": "klik/klik.png"
    },
    {
      "glob": "klik/lazy.png"
    },
    {
      "glob": "klik/light/bookmarks.png"
    },
    {
      "glob": "klik/light/folder.png"
    },
    {
      "glob": "klik/light/image.png"
    },
    {
      "glob": "klik/light/light.css"
    },
    {
      "glob": "klik/light/preferences.png"
    },
    {
      "glob": "klik/light/trash.png"
    },
    {
      "glob": "klik/light/up.png"
    },
    {
      "glob": "klik/light/view.png"
    },
    {
      "glob": "klik/running_film.gif"
    },
    {
      "glob": "lazy.png"
    },
    {
      "glob": "libglass.dylib"
    },
    {
      "glob": "libjavafx_font.dylib"
    },
    {
      "glob": "libjavafx_iio.dylib"
    },
    {
      "glob": "libprism_es2.dylib"
    },
    {
      "glob": "light/bookmarks.png"
    },
    {
      "glob": "light/folder.png"
    },
    {
      "glob": "light/image.png"
    },
    {
      "glob": "light/light.css"
    },
    {
      "glob": "light/preferences.png"
    },
    {
      "glob": "light/trash.png"
    },
    {
      "glob": "light/up.png"
    },
    {
      "glob": "light/view.png"
    },
    {
      "glob": "running_film.gif"
    },
    {
      "module": "java.base",
      "glob": "jdk/internal/icu/impl/data/icudt76b/ubidi.icu"
    },
    {
      "module": "java.desktop",
      "glob": "sun/awt/resources/awt_en.properties"
    },
    {
      "module": "java.desktop",
      "glob": "sun/awt/resources/awt_en_US.properties"
    },
    {
      "module": "java.desktop",
      "glob": "sun/awt/resources/awtosx_en.properties"
    },
    {
      "module": "java.desktop",
      "glob": "sun/awt/resources/awtosx_en_US.properties"
    },
    {
      "module": "java.logging",
      "glob": "sun/util/logging/resources/logging_en.properties"
    },
    {
      "module": "java.logging",
      "glob": "sun/util/logging/resources/logging_en_US.properties"
    },
    {
      "module": "java.xml",
      "glob": "com/sun/org/apache/xerces/internal/impl/msg/SAXMessages.properties"
    },
    {
      "module": "java.xml",
      "glob": "com/sun/org/apache/xerces/internal/impl/msg/SAXMessages_en.properties"
    },
    {
      "module": "java.xml",
      "glob": "com/sun/org/apache/xerces/internal/impl/msg/SAXMessages_en_US.properties"
    },
    {
      "module": "java.xml",
      "glob": "jdk/xml/internal/jdkcatalog/JDKCatalog.xml"
    }
  ],
  "bundles": [
    {
      "name": "com.sun.javafx.tk.quantum.QuantumMessagesBundle",
      "locales": [
        "en-US"
      ]
    },
    {
      "name": "com.sun.org.apache.xerces.internal.impl.msg.SAXMessages",
      "locales": [
        "en-US"
      ]
    },
    {
      "name": "com/sun/javafx/scene/control/skin/resources/controls",
      "locales": [
        "en-US"
      ]
    },
    {
      "name": "klik/MessagesBundle",
      "locales": [
        "en-US"
      ]
    },
    {
      "name": "sun.awt.resources.awt",
      "locales": [
        "en-US"
      ]
    },
    {
      "name": "sun.awt.resources.awtosx",
      "locales": [
        "en-US"
      ]
    }
  ],
  "jni": [
    {
      "type": "[Lcom.sun.glass.ui.Screen;"
    },
    {
      "type": "[Ljava.lang.String;"
    },
    {
      "type": "[Ljavafx.scene.paint.Color;"
    },
    {
      "type": "[Lsun.java2d.loops.GraphicsPrimitive;"
    },
    {
      "type": "com.sun.glass.ui.Application",
      "methods": [
        {
          "name": "notifyDidBecomeActive",
          "parameterTypes": []
        },
        {
          "name": "notifyDidFinishLaunching",
          "parameterTypes": []
        },
        {
          "name": "notifyOpenFiles",
          "parameterTypes": [
            "java.lang.String[]"
          ]
        },
        {
          "name": "notifyWillBecomeActive",
          "parameterTypes": []
        },
        {
          "name": "notifyWillFinishLaunching",
          "parameterTypes": []
        }
      ]
    },
    {
      "type": "com.sun.glass.ui.Menu",
      "methods": [
        {
          "name": "notifyMenuClosed",
          "parameterTypes": []
        },
        {
          "name": "notifyMenuOpening",
          "parameterTypes": []
        }
      ]
    },
    {
      "type": "com.sun.glass.ui.MenuItem$Callback",
      "methods": [
        {
          "name": "action",
          "parameterTypes": []
        },
        {
          "name": "validate",
          "parameterTypes": []
        }
      ]
    },
    {
      "type": "com.sun.glass.ui.Screen",
      "methods": [
        {
          "name": "<init>",
          "parameterTypes": [
            "long",
            "int",
            "int",
            "int",
            "int",
            "int",
            "int",
            "int",
            "int",
            "int",
            "int",
            "int",
            "int",
            "int",
            "int",
            "int",
            "float",
            "float",
            "float",
            "float"
          ]
        }
      ]
    },
    {
      "type": "com.sun.glass.ui.Size",
      "methods": [
        {
          "name": "<init>",
          "parameterTypes": [
            "int",
            "int"
          ]
        }
      ]
    },
    {
      "type": "com.sun.glass.ui.View",
      "fields": [
        {
          "name": "ptr"
        }
      ],
      "methods": [
        {
          "name": "getAccessible",
          "parameterTypes": []
        },
        {
          "name": "notifyDragDrop",
          "parameterTypes": [
            "int",
            "int",
            "int",
            "int",
            "int"
          ]
        },
        {
          "name": "notifyDragEnd",
          "parameterTypes": [
            "int"
          ]
        },
        {
          "name": "notifyDragEnter",
          "parameterTypes": [
            "int",
            "int",
            "int",
            "int",
            "int"
          ]
        },
        {
          "name": "notifyDragLeave",
          "parameterTypes": []
        },
        {
          "name": "notifyDragOver",
          "parameterTypes": [
            "int",
            "int",
            "int",
            "int",
            "int"
          ]
        },
        {
          "name": "notifyInputMethod",
          "parameterTypes": [
            "java.lang.String",
            "int[]",
            "int[]",
            "byte[]",
            "int",
            "int",
            "int"
          ]
        },
        {
          "name": "notifyInputMethodCandidatePosRequest",
          "parameterTypes": [
            "int"
          ]
        },
        {
          "name": "notifyKeyAndReturnConsumed",
          "parameterTypes": [
            "int",
            "int",
            "char[]",
            "int"
          ]
        },
        {
          "name": "notifyMenu",
          "parameterTypes": [
            "int",
            "int",
            "int",
            "int",
            "boolean"
          ]
        },
        {
          "name": "notifyMouse",
          "parameterTypes": [
            "int",
            "int",
            "int",
            "int",
            "int",
            "int",
            "int",
            "boolean",
            "boolean"
          ]
        },
        {
          "name": "notifyRepaint",
          "parameterTypes": [
            "int",
            "int",
            "int",
            "int"
          ]
        },
        {
          "name": "notifyResize",
          "parameterTypes": [
            "int",
            "int"
          ]
        },
        {
          "name": "notifyView",
          "parameterTypes": [
            "int"
          ]
        }
      ]
    },
    {
      "type": "com.sun.javafx.font.coretext.CGAffineTransform",
      "fields": [
        {
          "name": "a"
        },
        {
          "name": "b"
        },
        {
          "name": "c"
        },
        {
          "name": "d"
        },
        {
          "name": "tx"
        },
        {
          "name": "ty"
        }
      ],
      "methods": [
        {
          "name": "<init>",
          "parameterTypes": []
        }
      ]
    },
    {
      "type": "com.sun.javafx.font.coretext.CGPoint",
      "fields": [
        {
          "name": "x"
        },
        {
          "name": "y"
        }
      ],
      "methods": [
        {
          "name": "<init>",
          "parameterTypes": []
        }
      ]
    },
    {
      "type": "com.sun.javafx.font.coretext.CGRect",
      "fields": [
        {
          "name": "origin"
        },
        {
          "name": "size"
        }
      ],
      "methods": [
        {
          "name": "<init>",
          "parameterTypes": []
        }
      ]
    },
    {
      "type": "com.sun.javafx.font.coretext.CGSize",
      "fields": [
        {
          "name": "height"
        },
        {
          "name": "width"
        }
      ],
      "methods": [
        {
          "name": "<init>",
          "parameterTypes": []
        }
      ]
    },
    {
      "type": "com.sun.javafx.iio.common.ImageLoaderImpl",
      "methods": [
        {
          "name": "emitWarning",
          "parameterTypes": [
            "java.lang.String"
          ]
        }
      ]
    },
    {
      "type": "com.sun.javafx.iio.jpeg.JPEGImageLoader",
      "methods": [
        {
          "name": "setInputAttributes",
          "parameterTypes": [
            "int",
            "int",
            "int",
            "int",
            "int",
            "byte[]"
          ]
        },
        {
          "name": "setOutputAttributes",
          "parameterTypes": [
            "int",
            "int"
          ]
        },
        {
          "name": "updateImageProgress",
          "parameterTypes": [
            "int"
          ]
        }
      ]
    },
    {
      "type": "java.awt.AlphaComposite",
      "fields": [
        {
          "name": "extraAlpha"
        },
        {
          "name": "rule"
        }
      ]
    },
    {
      "type": "java.awt.Color",
      "methods": [
        {
          "name": "getRGB",
          "parameterTypes": []
        }
      ]
    },
    {
      "type": "java.awt.DisplayMode",
      "methods": [
        {
          "name": "<init>",
          "parameterTypes": [
            "int",
            "int",
            "int",
            "int"
          ]
        }
      ]
    },
    {
      "type": "java.awt.event.InputEvent",
      "methods": [
        {
          "name": "getButtonDownMasks",
          "parameterTypes": []
        }
      ]
    },
    {
      "type": "java.awt.geom.AffineTransform",
      "fields": [
        {
          "name": "m00"
        },
        {
          "name": "m01"
        },
        {
          "name": "m02"
        },
        {
          "name": "m10"
        },
        {
          "name": "m11"
        },
        {
          "name": "m12"
        }
      ]
    },
    {
      "type": "java.awt.geom.Path2D",
      "fields": [
        {
          "name": "numTypes"
        },
        {
          "name": "pointTypes"
        },
        {
          "name": "windingRule"
        }
      ]
    },
    {
      "type": "java.awt.geom.Path2D$Float",
      "fields": [
        {
          "name": "floatCoords"
        }
      ]
    },
    {
      "type": "java.awt.geom.Rectangle2D$Double",
      "methods": [
        {
          "name": "<init>",
          "parameterTypes": [
            "double",
            "double",
            "double",
            "double"
          ]
        }
      ]
    },
    {
      "type": "java.awt.image.BufferedImage",
      "fields": [
        {
          "name": "colorModel"
        },
        {
          "name": "imageType"
        },
        {
          "name": "raster"
        }
      ],
      "methods": [
        {
          "name": "getRGB",
          "parameterTypes": [
            "int",
            "int",
            "int",
            "int",
            "int[]",
            "int",
            "int"
          ]
        },
        {
          "name": "setRGB",
          "parameterTypes": [
            "int",
            "int",
            "int",
            "int",
            "int[]",
            "int",
            "int"
          ]
        }
      ]
    },
    {
      "type": "java.awt.image.ColorModel",
      "fields": [
        {
          "name": "colorSpace"
        },
        {
          "name": "colorSpaceType"
        },
        {
          "name": "isAlphaPremultiplied"
        },
        {
          "name": "is_sRGB"
        },
        {
          "name": "nBits"
        },
        {
          "name": "numComponents"
        },
        {
          "name": "supportsAlpha"
        },
        {
          "name": "transparency"
        }
      ],
      "methods": [
        {
          "name": "getRGBdefault",
          "parameterTypes": []
        }
      ]
    },
    {
      "type": "java.awt.image.IndexColorModel",
      "fields": [
        {
          "name": "allgrayopaque"
        },
        {
          "name": "colorData"
        },
        {
          "name": "map_size"
        },
        {
          "name": "rgb"
        },
        {
          "name": "transparent_index"
        }
      ]
    },
    {
      "type": "java.awt.image.Raster",
      "fields": [
        {
          "name": "dataBuffer"
        },
        {
          "name": "height"
        },
        {
          "name": "minX"
        },
        {
          "name": "minY"
        },
        {
          "name": "numBands"
        },
        {
          "name": "numDataElements"
        },
        {
          "name": "sampleModel"
        },
        {
          "name": "sampleModelTranslateX"
        },
        {
          "name": "sampleModelTranslateY"
        },
        {
          "name": "width"
        }
      ]
    },
    {
      "type": "java.awt.image.SampleModel",
      "fields": [
        {
          "name": "height"
        },
        {
          "name": "width"
        }
      ],
      "methods": [
        {
          "name": "getPixels",
          "parameterTypes": [
            "int",
            "int",
            "int",
            "int",
            "int[]",
            "java.awt.image.DataBuffer"
          ]
        },
        {
          "name": "setPixels",
          "parameterTypes": [
            "int",
            "int",
            "int",
            "int",
            "int[]",
            "java.awt.image.DataBuffer"
          ]
        }
      ]
    },
    {
      "type": "java.awt.image.SinglePixelPackedSampleModel",
      "fields": [
        {
          "name": "bitMasks"
        },
        {
          "name": "bitOffsets"
        },
        {
          "name": "bitSizes"
        },
        {
          "name": "maxBitSize"
        }
      ]
    },
    {
      "type": "java.io.InputStream",
      "methods": [
        {
          "name": "read",
          "parameterTypes": [
            "byte[]",
            "int",
            "int"
          ]
        },
        {
          "name": "skip",
          "parameterTypes": [
            "long"
          ]
        }
      ]
    },
    {
      "type": "java.lang.Boolean",
      "fields": [
        {
          "name": "FALSE"
        },
        {
          "name": "TRUE"
        }
      ],
      "methods": [
        {
          "name": "booleanValue",
          "parameterTypes": []
        },
        {
          "name": "getBoolean",
          "parameterTypes": [
            "java.lang.String"
          ]
        }
      ]
    },
    {
      "type": "java.lang.Class",
      "methods": [
        {
          "name": "forName",
          "parameterTypes": [
            "java.lang.String",
            "boolean",
            "java.lang.ClassLoader"
          ]
        }
      ]
    },
    {
      "type": "java.lang.Integer",
      "methods": [
        {
          "name": "<init>",
          "parameterTypes": [
            "int"
          ]
        },
        {
          "name": "intValue",
          "parameterTypes": []
        }
      ]
    },
    {
      "type": "java.lang.Long",
      "methods": [
        {
          "name": "longValue",
          "parameterTypes": []
        }
      ]
    },
    {
      "type": "java.lang.Object",
      "methods": [
        {
          "name": "equals",
          "parameterTypes": [
            "java.lang.Object"
          ]
        }
      ]
    },
    {
      "type": "java.lang.Runnable",
      "methods": [
        {
          "name": "run",
          "parameterTypes": []
        }
      ]
    },
    {
      "type": "java.lang.String"
    },
    {
      "type": "java.lang.System",
      "methods": [
        {
          "name": "getProperty",
          "parameterTypes": [
            "java.lang.String"
          ]
        },
        {
          "name": "load",
          "parameterTypes": [
            "java.lang.String"
          ]
        }
      ]
    },
    {
      "type": "java.util.Collections",
      "methods": [
        {
          "name": "unmodifiableMap",
          "parameterTypes": [
            "java.util.Map"
          ]
        }
      ]
    },
    {
      "type": "java.util.HashMap",
      "methods": [
        {
          "name": "<init>",
          "parameterTypes": []
        }
      ]
    },
    {
      "type": "java.util.List",
      "methods": [
        {
          "name": "add",
          "parameterTypes": [
            "java.lang.Object"
          ]
        }
      ]
    },
    {
      "type": "java.util.Map",
      "methods": [
        {
          "name": "get",
          "parameterTypes": [
            "java.lang.Object"
          ]
        },
        {
          "name": "put",
          "parameterTypes": [
            "java.lang.Object",
            "java.lang.Object"
          ]
        }
      ]
    },
    {
      "type": "javafx.scene.paint.Color",
      "methods": [
        {
          "name": "rgb",
          "parameterTypes": [
            "int",
            "int",
            "int",
            "double"
          ]
        }
      ]
    },
    {
      "type": "sun.awt.AWTAutoShutdown",
      "methods": [
        {
          "name": "notifyToolkitThreadFree",
          "parameterTypes": []
        }
      ]
    },
    {
      "type": "sun.awt.SunHints",
      "fields": [
        {
          "name": "INTVAL_STROKE_PURE"
        }
      ]
    },
    {
      "type": "sun.awt.image.BufImgSurfaceData$ICMColorData",
      "fields": [
        {
          "name": "pData"
        }
      ],
      "methods": [
        {
          "name": "<init>",
          "parameterTypes": [
            "long"
          ]
        }
      ]
    },
    {
      "type": "sun.awt.image.IntegerComponentRaster",
      "fields": [
        {
          "name": "data"
        },
        {
          "name": "dataOffsets"
        },
        {
          "name": "pixelStride"
        },
        {
          "name": "scanlineStride"
        },
        {
          "name": "type"
        }
      ]
    },
    {
      "type": "sun.java2d.Disposer",
      "methods": [
        {
          "name": "addRecord",
          "parameterTypes": [
            "java.lang.Object",
            "long",
            "long"
          ]
        }
      ]
    },
    {
      "type": "sun.java2d.InvalidPipeException"
    },
    {
      "type": "sun.java2d.NullSurfaceData"
    },
    {
      "type": "sun.java2d.SunGraphics2D",
      "fields": [
        {
          "name": "clipRegion"
        },
        {
          "name": "composite"
        },
        {
          "name": "eargb"
        },
        {
          "name": "lcdTextContrast"
        },
        {
          "name": "pixel"
        },
        {
          "name": "strokeHint"
        }
      ]
    },
    {
      "type": "sun.java2d.SurfaceData",
      "fields": [
        {
          "name": "pData"
        },
        {
          "name": "valid"
        }
      ]
    },
    {
      "type": "sun.java2d.loops.Blit",
      "methods": [
        {
          "name": "<init>",
          "parameterTypes": [
            "long",
            "sun.java2d.loops.SurfaceType",
            "sun.java2d.loops.CompositeType",
            "sun.java2d.loops.SurfaceType"
          ]
        }
      ]
    },
    {
      "type": "sun.java2d.loops.BlitBg",
      "methods": [
        {
          "name": "<init>",
          "parameterTypes": [
            "long",
            "sun.java2d.loops.SurfaceType",
            "sun.java2d.loops.CompositeType",
            "sun.java2d.loops.SurfaceType"
          ]
        }
      ]
    },
    {
      "type": "sun.java2d.loops.CompositeType",
      "fields": [
        {
          "name": "AnyAlpha"
        },
        {
          "name": "Src"
        },
        {
          "name": "SrcNoEa"
        },
        {
          "name": "SrcOver"
        },
        {
          "name": "SrcOverNoEa"
        },
        {
          "name": "Xor"
        }
      ]
    },
    {
      "type": "sun.java2d.loops.DrawGlyphList",
      "methods": [
        {
          "name": "<init>",
          "parameterTypes": [
            "long",
            "sun.java2d.loops.SurfaceType",
            "sun.java2d.loops.CompositeType",
            "sun.java2d.loops.SurfaceType"
          ]
        }
      ]
    },
    {
      "type": "sun.java2d.loops.DrawGlyphListAA",
      "methods": [
        {
          "name": "<init>",
          "parameterTypes": [
            "long",
            "sun.java2d.loops.SurfaceType",
            "sun.java2d.loops.CompositeType",
            "sun.java2d.loops.SurfaceType"
          ]
        }
      ]
    },
    {
      "type": "sun.java2d.loops.DrawGlyphListLCD",
      "methods": [
        {
          "name": "<init>",
          "parameterTypes": [
            "long",
            "sun.java2d.loops.SurfaceType",
            "sun.java2d.loops.CompositeType",
            "sun.java2d.loops.SurfaceType"
          ]
        }
      ]
    },
    {
      "type": "sun.java2d.loops.DrawLine",
      "methods": [
        {
          "name": "<init>",
          "parameterTypes": [
            "long",
            "sun.java2d.loops.SurfaceType",
            "sun.java2d.loops.CompositeType",
            "sun.java2d.loops.SurfaceType"
          ]
        }
      ]
    },
    {
      "type": "sun.java2d.loops.DrawParallelogram",
      "methods": [
        {
          "name": "<init>",
          "parameterTypes": [
            "long",
            "sun.java2d.loops.SurfaceType",
            "sun.java2d.loops.CompositeType",
            "sun.java2d.loops.SurfaceType"
          ]
        }
      ]
    },
    {
      "type": "sun.java2d.loops.DrawPath",
      "methods": [
        {
          "name": "<init>",
          "parameterTypes": [
            "long",
            "sun.java2d.loops.SurfaceType",
            "sun.java2d.loops.CompositeType",
            "sun.java2d.loops.SurfaceType"
          ]
        }
      ]
    },
    {
      "type": "sun.java2d.loops.DrawPolygons",
      "methods": [
        {
          "name": "<init>",
          "parameterTypes": [
            "long",
            "sun.java2d.loops.SurfaceType",
            "sun.java2d.loops.CompositeType",
            "sun.java2d.loops.SurfaceType"
          ]
        }
      ]
    },
    {
      "type": "sun.java2d.loops.DrawRect",
      "methods": [
        {
          "name": "<init>",
          "parameterTypes": [
            "long",
            "sun.java2d.loops.SurfaceType",
            "sun.java2d.loops.CompositeType",
            "sun.java2d.loops.SurfaceType"
          ]
        }
      ]
    },
    {
      "type": "sun.java2d.loops.FillParallelogram",
      "methods": [
        {
          "name": "<init>",
          "parameterTypes": [
            "long",
            "sun.java2d.loops.SurfaceType",
            "sun.java2d.loops.CompositeType",
            "sun.java2d.loops.SurfaceType"
          ]
        }
      ]
    },
    {
      "type": "sun.java2d.loops.FillPath",
      "methods": [
        {
          "name": "<init>",
          "parameterTypes": [
            "long",
            "sun.java2d.loops.SurfaceType",
            "sun.java2d.loops.CompositeType",
            "sun.java2d.loops.SurfaceType"
          ]
        }
      ]
    },
    {
      "type": "sun.java2d.loops.FillRect",
      "methods": [
        {
          "name": "<init>",
          "parameterTypes": [
            "long",
            "sun.java2d.loops.SurfaceType",
            "sun.java2d.loops.CompositeType",
            "sun.java2d.loops.SurfaceType"
          ]
        }
      ]
    },
    {
      "type": "sun.java2d.loops.FillSpans",
      "methods": [
        {
          "name": "<init>",
          "parameterTypes": [
            "long",
            "sun.java2d.loops.SurfaceType",
            "sun.java2d.loops.CompositeType",
            "sun.java2d.loops.SurfaceType"
          ]
        }
      ]
    },
    {
      "type": "sun.java2d.loops.GraphicsPrimitive",
      "fields": [
        {
          "name": "pNativePrim"
        }
      ]
    },
    {
      "type": "sun.java2d.loops.GraphicsPrimitiveMgr",
      "methods": [
        {
          "name": "register",
          "parameterTypes": [
            "sun.java2d.loops.GraphicsPrimitive[]"
          ]
        }
      ]
    },
    {
      "type": "sun.java2d.loops.MaskBlit",
      "methods": [
        {
          "name": "<init>",
          "parameterTypes": [
            "long",
            "sun.java2d.loops.SurfaceType",
            "sun.java2d.loops.CompositeType",
            "sun.java2d.loops.SurfaceType"
          ]
        }
      ]
    },
    {
      "type": "sun.java2d.loops.MaskFill",
      "methods": [
        {
          "name": "<init>",
          "parameterTypes": [
            "long",
            "sun.java2d.loops.SurfaceType",
            "sun.java2d.loops.CompositeType",
            "sun.java2d.loops.SurfaceType"
          ]
        }
      ]
    },
    {
      "type": "sun.java2d.loops.ScaledBlit",
      "methods": [
        {
          "name": "<init>",
          "parameterTypes": [
            "long",
            "sun.java2d.loops.SurfaceType",
            "sun.java2d.loops.CompositeType",
            "sun.java2d.loops.SurfaceType"
          ]
        }
      ]
    },
    {
      "type": "sun.java2d.loops.SurfaceType",
      "fields": [
        {
          "name": "Any3Byte"
        },
        {
          "name": "Any4Byte"
        },
        {
          "name": "AnyByte"
        },
        {
          "name": "AnyColor"
        },
        {
          "name": "AnyInt"
        },
        {
          "name": "AnyShort"
        },
        {
          "name": "ByteBinary1Bit"
        },
        {
          "name": "ByteBinary2Bit"
        },
        {
          "name": "ByteBinary4Bit"
        },
        {
          "name": "ByteGray"
        },
        {
          "name": "ByteIndexed"
        },
        {
          "name": "ByteIndexedBm"
        },
        {
          "name": "FourByteAbgr"
        },
        {
          "name": "FourByteAbgrPre"
        },
        {
          "name": "Index12Gray"
        },
        {
          "name": "Index8Gray"
        },
        {
          "name": "IntArgb"
        },
        {
          "name": "IntArgbBm"
        },
        {
          "name": "IntArgbPre"
        },
        {
          "name": "IntBgr"
        },
        {
          "name": "IntRgb"
        },
        {
          "name": "IntRgbx"
        },
        {
          "name": "OpaqueColor"
        },
        {
          "name": "ThreeByteBgr"
        },
        {
          "name": "Ushort4444Argb"
        },
        {
          "name": "Ushort555Rgb"
        },
        {
          "name": "Ushort555Rgbx"
        },
        {
          "name": "Ushort565Rgb"
        },
        {
          "name": "UshortGray"
        },
        {
          "name": "UshortIndexed"
        }
      ]
    },
    {
      "type": "sun.java2d.loops.TransformHelper",
      "methods": [
        {
          "name": "<init>",
          "parameterTypes": [
            "long",
            "sun.java2d.loops.SurfaceType",
            "sun.java2d.loops.CompositeType",
            "sun.java2d.loops.SurfaceType"
          ]
        }
      ]
    },
    {
      "type": "sun.java2d.loops.XORComposite",
      "fields": [
        {
          "name": "alphaMask"
        },
        {
          "name": "xorColor"
        },
        {
          "name": "xorPixel"
        }
      ]
    },
    {
      "type": "sun.java2d.pipe.Region",
      "fields": [
        {
          "name": "bands"
        },
        {
          "name": "endIndex"
        },
        {
          "name": "hix"
        },
        {
          "name": "hiy"
        },
        {
          "name": "lox"
        },
        {
          "name": "loy"
        }
      ]
    },
    {
      "type": "sun.java2d.pipe.RegionIterator",
      "fields": [
        {
          "name": "curIndex"
        },
        {
          "name": "numXbands"
        },
        {
          "name": "region"
        }
      ]
    },
    {
      "type": "sun.management.VMManagementImpl",
      "fields": [
        {
          "name": "compTimeMonitoringSupport"
        },
        {
          "name": "currentThreadCpuTimeSupport"
        },
        {
          "name": "objectMonitorUsageSupport"
        },
        {
          "name": "otherThreadCpuTimeSupport"
        },
        {
          "name": "remoteDiagnosticCommandsSupport"
        },
        {
          "name": "synchronizerUsageSupport"
        },
        {
          "name": "threadAllocatedMemorySupport"
        },
        {
          "name": "threadContentionMonitoringSupport"
        }
      ]
    }
  ]
}